elaina_flywheel-0.6.0.dist-info/METADATA
elaina_flywheel-0.6.0.dist-info/WHEEL
flywheel/__init__.py
flywheel/context.py
flywheel/entity.py
flywheel/fn/__init__.py
flywheel/fn/endpoint.py
flywheel/fn/implement.py
flywheel/fn/overload.py
flywheel/fn/record.py
flywheel/fn/selection.py
flywheel/globals.py
flywheel/instance_of.py
flywheel/overloads.py
flywheel/scoped.py
flywheel/typing.py
flywheel/userspace/__init__.py
flywheel/userspace/anycast.py
elaina_flywheel-0.6.0.dist-info/RECORD
