Metadata-Version: 2.1
Name: elaina-flywheel
Version: 0.6.0
Author-Email: Elaina <GreyElaina@outlook.com>
License: MIT
Requires-Python: >=3.9
Requires-Dist: typing-extensions>=4.10.0
